sdkBraspag/__init__.py
sdkBraspag/Auth/Auth.py
sdkBraspag/Auth/ExceptionsAuth.py
sdkBraspag/Auth/__init__.py
sdkBraspag/Enums/AttachmentType.py
sdkBraspag/Enums/BankAccountType.py
sdkBraspag/Enums/DocumentType.py
sdkBraspag/Enums/Product.py
sdkBraspag/Enums/__init__.py
sdkBraspag/Onboarding/ExceptionOnboarding.py
sdkBraspag/Onboarding/Onboarding.py
sdkBraspag/Onboarding/PaymentArrangement.py
sdkBraspag/Onboarding/__init__.py
sdkBraspag-0.0.3.dist-info/LICENSE.txt
sdkBraspag-0.0.3.dist-info/METADATA
sdkBraspag-0.0.3.dist-info/WHEEL
sdkBraspag-0.0.3.dist-info/top_level.txt
sdkBraspag-0.0.3.dist-info/RECORD
