Metadata-Version: 2.1
Name: sdkBraspag
Version: 0.0.3
Summary: Projeto de SDK para o Split de Pagamentos
Home-page: UNKNOWN
Author: Diego Faria
Author-email: diego.rdfaria@gmail.com
License: MIT
Keywords: SDK Braspag Split
Platform: UNKNOWN
Classifier: Development Status :: 1 - Planning
Classifier: Intended Audience :: Developers
Classifier: License :: OSI Approved :: MIT License
Classifier: Operating System :: OS Independent
Requires-Dist: requests
